odn/__init__.py
odn/base-odn.jpg
odn/base-odn_cut.jpg
odn/camera.py
odn/candidate_rois.txt
odn/dark_yolo.py
odn/filelist.txt
odn/fundus.py
odn/gui.py
odn/measure_map.py
odn/metrics.py
odn/model_classifier.png
odn/model_rpn.png
odn/models.txt
odn/requirements.txt
odn/rois.txt
odn/rois_naive.txt
odn/test_frcnn.py
odn/test_voc.py
odn/toastx.py
odn/train_frcnn.py
odn/train_rpn.py
odn/utilities.py
odn/vgg_rpn_loss_history.txt
odn/waiting_frame.py
odn/darkflow_yolo/__init__.py
odn/darkflow_yolo/cmd.txt
odn/darkflow_yolo/labels.txt
odn/darkflow_yolo/preview.png
odn/darkflow_yolo/setup.py
odn/darkflow_yolo/darkflow/__init__.py
odn/darkflow_yolo/darkflow/cli.py
odn/darkflow_yolo/darkflow/defaults.py
odn/darkflow_yolo/darkflow/version.py
odn/darkflow_yolo/darkflow/cython_utils/__init__.py
odn/darkflow_yolo/darkflow/cython_utils/cy_yolo2_findboxes.c
odn/darkflow_yolo/darkflow/cython_utils/cy_yolo2_findboxes.cp37-win_amd64.pyd
odn/darkflow_yolo/darkflow/cython_utils/cy_yolo2_findboxes.pyx
odn/darkflow_yolo/darkflow/cython_utils/cy_yolo_findboxes.c
odn/darkflow_yolo/darkflow/cython_utils/cy_yolo_findboxes.cp37-win_amd64.pyd
odn/darkflow_yolo/darkflow/cython_utils/cy_yolo_findboxes.pyx
odn/darkflow_yolo/darkflow/cython_utils/nms.c
odn/darkflow_yolo/darkflow/cython_utils/nms.cp37-win_amd64.pyd
odn/darkflow_yolo/darkflow/cython_utils/nms.pyx
odn/darkflow_yolo/darkflow/dark/__init__.py
odn/darkflow_yolo/darkflow/dark/connected.py
odn/darkflow_yolo/darkflow/dark/convolution.py
odn/darkflow_yolo/darkflow/dark/darknet.py
odn/darkflow_yolo/darkflow/dark/darkop.py
odn/darkflow_yolo/darkflow/dark/layer.py
odn/darkflow_yolo/darkflow/net/__init__.py
odn/darkflow_yolo/darkflow/net/build.py
odn/darkflow_yolo/darkflow/net/flow.py
odn/darkflow_yolo/darkflow/net/framework.py
odn/darkflow_yolo/darkflow/net/help.py
odn/darkflow_yolo/darkflow/net/ops/__init__.py
odn/darkflow_yolo/darkflow/net/ops/baseop.py
odn/darkflow_yolo/darkflow/net/ops/convolution.py
odn-0.4.6.dist-info/LICENSE
odn-0.4.6.dist-info/METADATA
odn-0.4.6.dist-info/WHEEL
odn-0.4.6.dist-info/top_level.txt
odn-0.4.6.dist-info/RECORD
