Metadata-Version: 2.1
Name: odn
Version: 0.4.6
Summary: A python library for object detection neural networks.
Home-page: https://github.com/zhangys11/odn
Author: Yinsheng Zhang (Ph.D.)
Author-email: oo@zju.edu.cn
Project-URL: Bug Tracker, https://github.com/zhangys11/odn/issues
Classifier: Programming Language :: Python :: 3
Classifier: License :: OSI Approved :: GNU General Public License v3 (GPLv3)
Classifier: Operating System :: OS Independent
Classifier: Topic :: Scientific/Engineering :: Mathematics
Requires-Python: >=3.6
License-File: LICENSE
Requires-Dist: scikit-learn
Requires-Dist: scipy
Requires-Dist: uuid
Requires-Dist: pandas
Requires-Dist: matplotlib
Requires-Dist: numpy
Requires-Dist: plotly
Requires-Dist: keras
Requires-Dist: opencv-python
Requires-Dist: tf-slim
Requires-Dist: six
Requires-Dist: cython
Requires-Dist: tqdm
Requires-Dist: seaborn
